racing/__init__.py
racing/racing.py
report_racing_pack-0.0.1.dist-info/METADATA
report_racing_pack-0.0.1.dist-info/WHEEL
report_racing_pack-0.0.1.dist-info/top_level.txt
report_racing_pack-0.0.1.dist-info/RECORD
