Metadata-Version: 2.1
Name: report-racing-pack
Version: 0.0.1
Summary: Output the report of the best lap of riders in qualification
Home-page: https://git.foxminded.com.ua/foxstudent101900/task_6
Author: oleh.brailko
Author-email: oleh.brailko@gmail.com
Classifier: Programming Language :: Python :: 3
Classifier: License :: OSI Approved :: MIT License
Classifier: Operating System :: OS Independent
Requires-Python: >=3.8
